ipytangle/widgets.py
ipytangle/__init__.py
ipytangle/static/ipytangle/js/tangle_output.js
ipytangle/static/ipytangle/js/tangle_variable.js
ipytangle/static/ipytangle/js/tangle_if.js
ipytangle/static/ipytangle/js/tangle_view.js
ipytangle/static/ipytangle/lib/d3/README.md
ipytangle/static/ipytangle/lib/d3/.bower.json
ipytangle/static/ipytangle/lib/d3/package.js
ipytangle/static/ipytangle/lib/d3/bower.json
ipytangle/static/ipytangle/lib/d3/d3.min.js
ipytangle/static/ipytangle/lib/d3/.gitattributes
ipytangle/static/ipytangle/lib/d3/CONTRIBUTING.md
ipytangle/static/ipytangle/lib/d3/d3.js
ipytangle/static/ipytangle/lib/mathjs/ROADMAP.md
ipytangle/static/ipytangle/lib/mathjs/README.md
ipytangle/static/ipytangle/lib/mathjs/.bower.json
ipytangle/static/ipytangle/lib/mathjs/bower.json
ipytangle/static/ipytangle/lib/mathjs/composer.json
ipytangle/static/ipytangle/lib/mathjs/index.js
ipytangle/static/ipytangle/lib/mathjs/CONTRIBUTING.md
ipytangle/static/ipytangle/lib/mathjs/HISTORY.md
ipytangle/static/ipytangle/lib/mathjs/docs/chaining.md
ipytangle/static/ipytangle/lib/mathjs/docs/command_line_interface.md
ipytangle/static/ipytangle/lib/mathjs/docs/index.md
ipytangle/static/ipytangle/lib/mathjs/docs/getting_started.md
ipytangle/static/ipytangle/lib/mathjs/docs/configuration.md
ipytangle/static/ipytangle/lib/mathjs/docs/expressions.md
ipytangle/static/ipytangle/lib/mathjs/docs/extension.md
ipytangle/static/ipytangle/lib/mathjs/docs/serialization.md
ipytangle/static/ipytangle/lib/mathjs/docs/chained_operations.md
ipytangle/static/ipytangle/lib/mathjs/docs/introduction.md
ipytangle/static/ipytangle/lib/mathjs/docs/datatypes/complex_numbers.md
ipytangle/static/ipytangle/lib/mathjs/docs/datatypes/index.md
ipytangle/static/ipytangle/lib/mathjs/docs/datatypes/numbers.md
ipytangle/static/ipytangle/lib/mathjs/docs/datatypes/matrices.md
ipytangle/static/ipytangle/lib/mathjs/docs/datatypes/bignumbers.md
ipytangle-0.1.2.dist-info/WHEEL
ipytangle-0.1.2.dist-info/DESCRIPTION.rst
ipytangle-0.1.2.dist-info/metadata.json
ipytangle-0.1.2.dist-info/RECORD
ipytangle-0.1.2.dist-info/METADATA
ipytangle-0.1.2.dist-info/top_level.txt
