Metadata-Version: 2.0
Name: ipytangle
Version: 0.1.2
Summary: Tangle reactive documents in the IPython Notebook
Home-page: http://github.com/bollwyvl/ipytangle
Author: Nicholas Bollweg
Author-email: nick.bollweg@gmail.com
License: BSD
Keywords: IPython tangle
Platform: UNKNOWN
Classifier: Framework :: IPython
Classifier: Natural Language :: English
Classifier: Programming Language :: Python
Classifier: Intended Audience :: Developers
Classifier: Development Status :: 3 - Alpha
Classifier: Operating System :: OS Independent
Classifier: Programming Language :: Python :: 3
Classifier: Programming Language :: Python :: 2
Classifier: License :: OSI Approved :: BSD License
Classifier: Topic :: Software Development :: Widget Sets
Classifier: Topic :: Scientific/Engineering :: Human Machine Interfaces
Classifier: Topic :: Scientific/Engineering :: Visualization
Requires-Dist: IPython (>3.0,<4.0)
Requires-Dist: jupyter-pip
